django_generic/__init__.py
django_generic/db.py
django_generic/db_expressions.py
django_generic/factories.py
django_generic/images.py
django_generic/mixins.py
django_generic/time.py
django_generic/utils.py
django_generic-0.0.2.dist-info/METADATA
django_generic-0.0.2.dist-info/RECORD
django_generic-0.0.2.dist-info/WHEEL
django_generic-0.0.2.dist-info/top_level.txt
tests/__init__.py
tests/apps.py
tests/factories.py
tests/models.py
tests/settings.py
tests/urls.py
tests/tests/__init__.py
tests/tests/tests_db.py
